[
  {
    "id": "546ff1dc-4118-435c-aa4c-e71fd455e7c1",
    "data": [
      {
        "text": " bye ",
        "userDefined": false
      },
      {
        "text": "good",
        "meta": "@sys.ignore",
        "userDefined": true
      },
      {
        "text": " ",
        "userDefined": false
      },
      {
        "text": "night",
        "meta": "@sys.ignore",
        "userDefined": true
      }
    ],
    "isTemplate": false,
    "count": 0,
    "updated": 0
  },
  {
    "id": "9d21c6b9-2fc2-4f87-80f7-ef11ec693825",
    "data": [
      {
        "text": "goodnight",
        "userDefined": false
      }
    ],
    "isTemplate": false,
    "count": 0,
    "updated": 0
  },
  {
    "id": "2b415f62-d8fa-491a-9c9e-5e1328300bcf",
    "data": [
      {
        "text": "bye ",
        "userDefined": false
      },
      {
        "text": "good",
        "meta": "@sys.ignore",
        "userDefined": true
      },
      {
        "text": " ",
        "userDefined": false
      },
      {
        "text": "night",
        "meta": "@sys.ignore",
        "userDefined": true
      }
    ],
    "isTemplate": false,
    "count": 0,
    "updated": 0
  },
  {
    "id": "90e730df-d6b2-4b63-a598-8282f86363a0",
    "data": [
      {
        "text": "good",
        "meta": "@sys.ignore",
        "userDefined": true
      },
      {
        "text": " ",
        "userDefined": false
      },
      {
        "text": "night",
        "meta": "@sys.ignore",
        "userDefined": true
      },
      {
        "text": " bye",
        "userDefined": false
      }
    ],
    "isTemplate": false,
    "count": 0,
    "updated": 0
  },
  {
    "id": "2fddaafd-7e7f-4aa8-9d1e-39538c49a115",
    "data": [
      {
        "text": "good",
        "meta": "@sys.ignore",
        "userDefined": true
      },
      {
        "text": " ",
        "userDefined": false
      },
      {
        "text": "good",
        "meta": "@sys.ignore",
        "userDefined": true
      },
      {
        "text": " ",
        "userDefined": false
      },
      {
        "text": "night",
        "meta": "@sys.ignore",
        "userDefined": true
      }
    ],
    "isTemplate": false,
    "count": 0,
    "updated": 0
  },
  {
    "id": "409dc4e7-bb8d-4083-a271-36968853bf4f",
    "data": [
      {
        "text": "night",
        "meta": "@sys.ignore",
        "userDefined": false
      }
    ],
    "isTemplate": false,
    "count": 0,
    "updated": 0
  },
  {
    "id": "cfbf1300-5d2a-48b6-becc-4484f03f7140",
    "data": [
      {
        "text": "have a ",
        "userDefined": false
      },
      {
        "text": "good",
        "meta": "@sys.ignore",
        "userDefined": true
      },
      {
        "text": " ",
        "userDefined": false
      },
      {
        "text": "night",
        "meta": "@sys.ignore",
        "userDefined": true
      }
    ],
    "isTemplate": false,
    "count": 1,
    "updated": 0
  },
  {
    "id": "a6e63f02-aa7c-419d-91dc-9d08905b0866",
    "data": [
      {
        "text": "thanks goodnight",
        "userDefined": false
      }
    ],
    "isTemplate": false,
    "count": 0,
    "updated": 0
  },
  {
    "id": "201a168e-4f85-48f4-bbb9-5d729858d3ce",
    "data": [
      {
        "text": "thank you",
        "meta": "@sys.ignore",
        "userDefined": true
      },
      {
        "text": " good ",
        "userDefined": false
      },
      {
        "text": "night",
        "meta": "@sys.ignore",
        "userDefined": true
      }
    ],
    "isTemplate": false,
    "count": 0,
    "updated": 0
  },
  {
    "id": "e2c228a1-ea81-4b28-aff8-6cce57713b00",
    "data": [
      {
        "text": "good",
        "meta": "@sys.ignore",
        "userDefined": false
      },
      {
        "text": " ",
        "userDefined": false
      },
      {
        "text": "night",
        "meta": "@sys.ignore",
        "userDefined": false
      },
      {
        "text": " see you ",
        "userDefined": false
      },
      {
        "text": "tomorrow",
        "meta": "@sys.ignore",
        "userDefined": false
      }
    ],
    "isTemplate": false,
    "count": 0,
    "updated": 0
  },
  {
    "id": "9b21dce1-c358-4dc9-9183-fc3540e843fa",
    "data": [
      {
        "text": "good night for now",
        "userDefined": false
      }
    ],
    "isTemplate": false,
    "count": 0,
    "updated": 0
  },
  {
    "id": "c80b4c97-9499-47af-b11c-b63935747f44",
    "data": [
      {
        "text": "have a good night",
        "userDefined": false
      }
    ],
    "isTemplate": false,
    "count": 0,
    "updated": 0
  },
  {
    "id": "38f93d82-ee0b-41af-92ac-56b895714a73",
    "data": [
      {
        "text": "good",
        "meta": "@sys.ignore",
        "userDefined": true
      },
      {
        "text": " ",
        "userDefined": false
      },
      {
        "text": "night",
        "meta": "@sys.ignore",
        "userDefined": true
      }
    ],
    "isTemplate": false,
    "count": 0,
    "updated": 0
  },
  {
    "id": "941e1edb-6bd3-4ae6-a5d0-699fc02839da",
    "data": [
      {
        "text": "good",
        "meta": "@sys.ignore",
        "userDefined": true
      },
      {
        "text": " ",
        "userDefined": false
      },
      {
        "text": "night",
        "meta": "@sys.ignore",
        "userDefined": true
      },
      {
        "text": " to you",
        "userDefined": false
      }
    ],
    "isTemplate": false,
    "count": 0,
    "updated": 0
  },
  {
    "id": "cb619c79-c0e4-4197-ab62-6bd9c73cb85e",
    "data": [
      {
        "text": "good",
        "meta": "@sys.ignore",
        "userDefined": false
      },
      {
        "text": " ",
        "userDefined": false
      },
      {
        "text": "tonight",
        "meta": "@sys.ignore",
        "userDefined": false
      }
    ],
    "isTemplate": false,
    "count": 0,
    "updated": 0
  },
  {
    "id": "0feb104b-600e-47c7-9f6b-0f555f5e0cc3",
    "data": [
      {
        "text": "okay have a good night",
        "userDefined": false
      }
    ],
    "isTemplate": false,
    "count": 0,
    "updated": 0
  },
  {
    "id": "8837f1d3-f2ed-42e6-992f-6390f366701b",
    "data": [
      {
        "text": "sweet dreams",
        "userDefined": false
      }
    ],
    "isTemplate": false,
    "count": 0,
    "updated": 0
  },
  {
    "id": "12f0d3a5-757a-491c-9ccc-f1dadc784e92",
    "data": [
      {
        "text": "night",
        "userDefined": false
      }
    ],
    "isTemplate": false,
    "count": 0,
    "updated": 0
  },
  {
    "id": "3c71711f-4865-4233-9ddf-8827cf477646",
    "data": [
      {
        "text": "alright goodnight",
        "userDefined": false
      }
    ],
    "isTemplate": false,
    "count": 0,
    "updated": 0
  }
]