[
  {
    "id": "31ec020f-ab77-4470-9ba9-b3d5d26df7a9",
    "data": [
      {
        "text": "I am feeling ",
        "userDefined": false
      },
      {
        "text": "lonely",
        "meta": "@sys.ignore",
        "userDefined": false
      }
    ],
    "isTemplate": false,
    "count": 0,
    "updated": 0
  },
  {
    "id": "d2e2ecda-d676-422d-bf24-122734df97b6",
    "data": [
      {
        "text": "I am ",
        "userDefined": false
      },
      {
        "text": "lonely",
        "meta": "@sys.ignore",
        "userDefined": false
      }
    ],
    "isTemplate": false,
    "count": 0,
    "updated": 0
  },
  {
    "id": "44401561-89d2-4dbe-86f3-c02c3b9b2b41",
    "data": [
      {
        "text": "I ",
        "userDefined": false
      },
      {
        "text": "feel",
        "meta": "@sys.ignore",
        "userDefined": false
      },
      {
        "text": " ",
        "userDefined": false
      },
      {
        "text": "lonely",
        "meta": "@sys.ignore",
        "userDefined": false
      }
    ],
    "isTemplate": false,
    "count": 0,
    "updated": 0
  },
  {
    "id": "a1b25a83-6878-466b-be31-73289d0a13ed",
    "data": [
      {
        "text": "I\u0027m really ",
        "userDefined": false
      },
      {
        "text": "lonely",
        "meta": "@sys.ignore",
        "userDefined": false
      }
    ],
    "isTemplate": false,
    "count": 0,
    "updated": 0
  },
  {
    "id": "4e135476-5d9e-42cf-95f4-8b438b4e3100",
    "data": [
      {
        "text": "I\u0027m very ",
        "userDefined": false
      },
      {
        "text": "lonely",
        "meta": "@sys.ignore",
        "userDefined": false
      }
    ],
    "isTemplate": false,
    "count": 0,
    "updated": 0
  },
  {
    "id": "45b3e3c6-28f4-47de-8eaa-22276a1b7afa",
    "data": [
      {
        "text": "I\u0027m so ",
        "userDefined": false
      },
      {
        "text": "lonely",
        "meta": "@sys.ignore",
        "userDefined": false
      }
    ],
    "isTemplate": false,
    "count": 0,
    "updated": 0
  }
]